non_restoring_division_stage.v
module non_restoring_division_stage (

    input wire [7:0] A_in,
    input wire [7:0] Q_in,
    input wire [7:0] M,
    output wire [7:0] A_out,
    output reg [7:0] Q_out

);
wire [7:0] A_1;
wire [7:0] Q_1;
reg [7:0] M_1;

assign {A_1[7:0], Q_1[7:0]} = {A_in[6:0], Q_in[7:0], 1'b0};
    always @(*) begin
        if (A_in[7] == 0) begin
            M_1[7:0] = ~M[7:0] + 1'b1; 
        end else begin
            M_1[7:0] = M[7:0];
        end
    end

assign A_out = M_1 + A_1;

    always @(*) begin
        if (A_out[7] == 0) begin
            Q_out[7:0] = {Q_1[7:1], 1'b1};
        end else begin
            Q_out[7:0] = {Q_1[7:1], 1'b0};
        end
    end


endmodule

non_restoring_division_8bit.v
`include "non_restoring_division_stage.v"
module non_restoring_division_8bit (

    input [7:0] QQ,
    input [7:0] M,
    output reg [7:0] quotient,
    output reg [7:0] remainder 
);

wire [7:0] AA;
wire [7:0] AA0;
wire [7:0] QQ0;
assign AA = 8'b0;
non_restoring_division_stage stage0 (.A_in(AA),.Q_in(QQ),.M(M),.A_out(AA0),.Q_out(QQ0));

wire [7:0] AA1;
wire [7:0] QQ1;
non_restoring_division_stage stage1 (.A_in(AA0),.Q_in(QQ0),.M(M),.A_out(AA1),.Q_out(QQ1));

wire [7:0] AA2;
wire [7:0] QQ2;
non_restoring_division_stage stage2 (.A_in(AA1),.Q_in(QQ1),.M(M),.A_out(AA2),.Q_out(QQ2));

wire [7:0] AA3;
wire [7:0] QQ3;
non_restoring_division_stage stage3 (.A_in(AA2),.Q_in(QQ2),.M(M),.A_out(AA3),.Q_out(QQ3));

wire [7:0] AA4;
wire [7:0] QQ4; 
non_restoring_division_stage stage4 (.A_in(AA3),.Q_in(QQ3),.M(M),.A_out(AA4),.Q_out(QQ4));

wire [7:0] AA5;
wire [7:0] QQ5; 
non_restoring_division_stage stage5 (.A_in(AA4),.Q_in(QQ4),.M(M),.A_out(AA5),.Q_out(QQ5));

wire [7:0] AA6;
wire [7:0] QQ6;
non_restoring_division_stage stage6 (.A_in(AA5),.Q_in(QQ5),.M(M),.A_out(AA6),.Q_out(QQ6));

wire [7:0] AA7;
wire [7:0] QQ7;
non_restoring_division_stage stage7 (.A_in(AA6),.Q_in(QQ6),.M(M),.A_out(AA7),.Q_out(QQ7));



always @(AA7) begin
     quotient = QQ7;
    if (AA7[7]) begin
        remainder <= AA7 + M;
    end else begin
        remainder <= AA7;
    end
end
    
endmodule

PROCESSOR/NON_PIPELINED/ALU_UNIT/DIVIDER/non_restoring_division_8bit_tb.v
`include "non_restoring_division_8bit.v"

module tb_non_restoring_division;
    reg [7:0] QQ;
    reg [7:0] M;
    wire [7:0] quotient;
    wire [7:0] remainder;

    non_restoring_division_8bit uut (
        .QQ(QQ),
        .M(M),
        .quotient(quotient),
        .remainder(remainder)
    );

    initial begin
        $dumpfile("non_restoring_division.vcd");
        $dumpvars(0, tb_non_restoring_division);

        $monitor("QQ=%d M=%d Q=%d R=%d", QQ, M, quotient, remainder);

        QQ = 8'd20;  M = 8'd5;   #10;
        QQ = 8'd27;  M = 8'd4;   #10;
        QQ = 8'd255; M = 8'd10;  #10;
        QQ = 8'd50;  M = 8'd1;   #10;
        QQ = 8'd5;   M = 8'd10;  #10;
        QQ = 8'd160; M = 8'd3;   #10;
        QQ = 8'd100; M = 8'd128; #10;
        QQ = 8'd127; M = 8'd127; #10;

        $finish;
    end
endmodule

non_restoring_division.vcd
$date
	Thu Mar 12 00:01:24 2026
$end
$version
	Icarus Verilog
$end
$timescale
	1s
$end
$scope module tb_non_restoring_division $end
$var wire 8 ! remainder [7:0] $end
$var wire 8 " quotient [7:0] $end
$var reg 8 # M [7:0] $end
$var reg 8 $ QQ [7:0] $end
$scope module uut $end
$var wire 8 % AA [7:0] $end
$var wire 8 & M [7:0] $end
$var wire 8 ' QQ [7:0] $end
$var wire 8 ( QQ7 [7:0] $end
$var wire 8 ) QQ6 [7:0] $end
$var wire 8 * QQ5 [7:0] $end
$var wire 8 + QQ4 [7:0] $end
$var wire 8 , QQ3 [7:0] $end
$var wire 8 - QQ2 [7:0] $end
$var wire 8 . QQ1 [7:0] $end
$var wire 8 / QQ0 [7:0] $end
$var wire 8 0 AA7 [7:0] $end
$var wire 8 1 AA6 [7:0] $end
$var wire 8 2 AA5 [7:0] $end
$var wire 8 3 AA4 [7:0] $end
$var wire 8 4 AA3 [7:0] $end
$var wire 8 5 AA2 [7:0] $end
$var wire 8 6 AA1 [7:0] $end
$var wire 8 7 AA0 [7:0] $end
$var reg 8 8 quotient [7:0] $end
$var reg 8 9 remainder [7:0] $end
$scope module stage0 $end
$var wire 8 : A_in [7:0] $end
$var wire 8 ; M [7:0] $end
$var wire 8 < Q_in [7:0] $end
$var wire 8 = Q_1 [7:0] $end
$var wire 8 > A_out [7:0] $end
$var wire 8 ? A_1 [7:0] $end
$var reg 8 @ M_1 [7:0] $end
$var reg 8 A Q_out [7:0] $end
$upscope $end
$scope module stage1 $end
$var wire 8 B A_in [7:0] $end
$var wire 8 C M [7:0] $end
$var wire 8 D Q_in [7:0] $end
$var wire 8 E Q_1 [7:0] $end
$var wire 8 F A_out [7:0] $end
$var wire 8 G A_1 [7:0] $end
$var reg 8 H M_1 [7:0] $end
$var reg 8 I Q_out [7:0] $end
$upscope $end
$scope module stage2 $end
$var wire 8 J A_in [7:0] $end
$var wire 8 K M [7:0] $end
$var wire 8 L Q_in [7:0] $end
$var wire 8 M Q_1 [7:0] $end
$var wire 8 N A_out [7:0] $end
$var wire 8 O A_1 [7:0] $end
$var reg 8 P M_1 [7:0] $end
$var reg 8 Q Q_out [7:0] $end
$upscope $end
$scope module stage3 $end
$var wire 8 R A_in [7:0] $end
$var wire 8 S M [7:0] $end
$var wire 8 T Q_in [7:0] $end
$var wire 8 U Q_1 [7:0] $end
$var wire 8 V A_out [7:0] $end
$var wire 8 W A_1 [7:0] $end
$var reg 8 X M_1 [7:0] $end
$var reg 8 Y Q_out [7:0] $end
$upscope $end
$scope module stage4 $end
$var wire 8 Z A_in [7:0] $end
$var wire 8 [ M [7:0] $end
$var wire 8 \ Q_in [7:0] $end
$var wire 8 ] Q_1 [7:0] $end
$var wire 8 ^ A_out [7:0] $end
$var wire 8 _ A_1 [7:0] $end
$var reg 8 ` M_1 [7:0] $end
$var reg 8 a Q_out [7:0] $end
$upscope $end
$scope module stage5 $end
$var wire 8 b A_in [7:0] $end
$var wire 8 c M [7:0] $end
$var wire 8 d Q_in [7:0] $end
$var wire 8 e Q_1 [7:0] $end
$var wire 8 f A_out [7:0] $end
$var wire 8 g A_1 [7:0] $end
$var reg 8 h M_1 [7:0] $end
$var reg 8 i Q_out [7:0] $end
$upscope $end
$scope module stage6 $end
$var wire 8 j A_in [7:0] $end
$var wire 8 k M [7:0] $end
$var wire 8 l Q_in [7:0] $end
$var wire 8 m Q_1 [7:0] $end
$var wire 8 n A_out [7:0] $end
$var wire 8 o A_1 [7:0] $end
$var reg 8 p M_1 [7:0] $end
$var reg 8 q Q_out [7:0] $end
$upscope $end
$scope module stage7 $end
$var wire 8 r A_in [7:0] $end
$var wire 8 s M [7:0] $end
$var wire 8 t Q_in [7:0] $end
$var wire 8 u Q_1 [7:0] $end
$var wire 8 v A_out [7:0] $end
$var wire 8 w A_1 [7:0] $end
$var reg 8 x M_1 [7:0] $end
$var reg 8 y Q_out [7:0] $end
$upscope $end
$upscope $end
$upscope $end
$enddefinitions $end
$comment Show the parameter values. $end
$dumpall
$end
#0
$dumpvars
b100 y
b101 x
b11110110 w
b11111011 v
b100 u
b10 t
b101 s
b11111011 r
b10 q
b11111011 p
b0 o
b11111011 n
b10 m
b1 l
b101 k
b0 j
b1 i
b101 h
b11111011 g
b0 f
b0 e
b10000000 d
b101 c
b11111101 b
b10000000 a
b101 `
b11111000 _
b11111101 ^
b10000000 ]
b1000000 \
b101 [
b11111100 Z
b1000000 Y
b101 X
b11110111 W
b11111100 V
b1000000 U
b10100000 T
b101 S
b11111011 R
b10100000 Q
b101 P
b11110110 O
b11111011 N
b10100000 M
b1010000 L
b101 K
b11111011 J
b1010000 I
b101 H
b11110110 G
b11111011 F
b1010000 E
b101000 D
b101 C
b11111011 B
b101000 A
b11111011 @
b0 ?
b11111011 >
b101000 =
b10100 <
b101 ;
b0 :
b0 9
b100 8
b11111011 7
b11111011 6
b11111011 5
b11111100 4
b11111101 3
b0 2
b11111011 1
b11111011 0
b101000 /
b1010000 .
b10100000 -
b1000000 ,
b10000000 +
b1 *
b10 )
b100 (
b10100 '
b101 &
b0 %
b10100 $
b101 #
b100 "
b0 !
$end
#10
b11 !
b11 9
b11000000 e
b1100000 +
b1100000 a
b1100000 d
b1100000 ]
b10110000 ,
b10110000 Y
b10110000 \
b10110000 U
b11011000 -
b11011000 Q
b11011000 T
b110 "
b110 8
b110 (
b110 y
b11011000 M
b110 u
b1101100 .
b1101100 I
b1101100 L
b11111000 G
b11111000 O
b11111001 W
b11111011 _
b11111110 g
b101 o
b10000010 m
b10000011 )
b10000011 q
b10000011 t
b11 w
b1101100 E
b11000001 *
b11000001 i
b11000001 l
b110110 /
b110110 A
b110110 D
b11111100 7
b11111100 >
b11111100 B
b11111100 @
b11111100 6
b11111100 F
b11111100 J
b100 H
b11111100 5
b11111100 N
b11111100 R
b100 P
b11111101 4
b11111101 V
b11111101 Z
b100 X
b11111111 3
b11111111 ^
b11111111 b
b100 `
b10 2
b10 f
b10 j
b100 h
b1 1
b1 n
b1 r
b11111100 p
b11111111 0
b11111111 v
b11111100 x
b110110 =
b100 #
b100 &
b100 ;
b100 C
b100 K
b100 S
b100 [
b100 c
b100 k
b100 s
b11011 $
b11011 '
b11011 <
#20
b101 !
b101 9
b10001100 m
b11110011 O
b11111000 M
b11111011 W
b11110000 U
b1011 _
b11100010 ]
b11 g
b11000110 e
b11000110 *
b11000110 i
b11000110 l
b11110011 o
b11111011 w
b11000 u
b11001 "
b11001 8
b11001 (
b11001 y
b11111100 E
b11101111 G
b11111100 .
b11111100 I
b11111100 L
b11111000 -
b11111000 Q
b11111000 T
b11110001 ,
b11110001 Y
b11110001 \
b11100011 +
b11100011 a
b11100011 d
b10001100 )
b10001100 q
b10001100 t
b11111110 /
b11111110 A
b11111110 D
b11110110 @
b11111001 6
b11111001 F
b11111001 J
b1010 H
b11111101 5
b11111101 N
b11111101 R
b1010 P
b101 4
b101 V
b101 Z
b1010 X
b1 3
b1 ^
b1 b
b11110110 `
b11111001 2
b11111001 f
b11111001 j
b11110110 h
b11111101 1
b11111101 n
b11111101 r
b1010 p
b101 0
b101 v
b1010 x
b11111110 =
b11110111 7
b11110111 >
b11110111 B
b1 ?
b1010 #
b1010 &
b1010 ;
b1010 C
b1010 K
b1010 S
b1010 [
b1010 c
b1010 k
b1010 s
b11111111 $
b11111111 '
b11111111 <
#30
b0 !
b0 9
b100010 U
b10010001 -
b10010001 Q
b10010001 T
b10001100 e
b110010 u
b10010000 M
b1000110 +
b1000110 a
b1000110 d
b11001 )
b11001 q
b11001 t
b11001000 .
b11001000 I
b11001000 L
b11111111 O
b1 W
b0 _
b1000110 ]
b11111110 g
b11111111 o
b11000 m
b0 w
b11001000 E
b11111110 G
b100011 ,
b100011 Y
b100011 \
b10001100 *
b10001100 i
b10001100 l
b110010 "
b110010 8
b110010 (
b110010 y
b1100100 /
b1100100 A
b1100100 D
b11111111 @
b11111111 6
b11111111 F
b11111111 J
b1 H
b0 5
b0 N
b0 R
b1 P
b0 4
b0 V
b0 Z
b11111111 X
b11111111 3
b11111111 ^
b11111111 b
b11111111 `
b11111111 2
b11111111 f
b11111111 j
b1 h
b0 1
b0 n
b0 r
b1 p
b11111111 0
b11111111 v
b11111111 x
b1100100 =
b11111111 7
b11111111 >
b11111111 B
b0 ?
b1 #
b1 &
b1 ;
b1 C
b1 K
b1 S
b1 [
b1 c
b1 k
b1 s
b110010 $
b110010 '
b110010 <
#40
b101 !
b101 9
b1010000 U
b1000000 e
b0 u
b0 "
b0 8
b0 (
b0 y
b11101100 G
b11101100 O
b101000 M
b101000 -
b101000 Q
b101000 T
b11101100 W
b11101100 _
b10100000 ]
b10100000 +
b10100000 a
b10100000 d
b11101101 g
b11101110 o
b10000000 m
b10000000 )
b10000000 q
b10000000 t
b11110001 w
b10100 E
b10100 .
b10100 I
b10100 L
b1010000 ,
b1010000 Y
b1010000 \
b1000000 *
b1000000 i
b1000000 l
b1010 /
b1010 A
b1010 D
b11110110 7
b11110110 >
b11110110 B
b11110110 @
b11110110 6
b11110110 F
b11110110 J
b1010 H
b11110110 5
b11110110 N
b11110110 R
b1010 P
b11110110 4
b11110110 V
b11110110 Z
b1010 X
b11110110 3
b11110110 ^
b11110110 b
b1010 `
b11110111 2
b11110111 f
b11110111 j
b1010 h
b11111000 1
b11111000 n
b11111000 r
b1010 p
b11111011 0
b11111011 v
b1010 x
b1010 =
b1010 #
b1010 &
b1010 ;
b1010 C
b1010 K
b1010 S
b1010 [
b1010 c
b1010 k
b1010 s
b101 $
b101 '
b101 <
#50
b1 !
b1 9
b11010 m
b110100 u
b1101 *
b1101 i
b1101 l
b11010 )
b11010 q
b11010 t
b110101 "
b110101 8
b110101 (
b110101 y
b1100 e
b110 ]
b110 +
b110 a
b110 d
b11 ,
b11 Y
b11 \
b10 U
b1 -
b1 Q
b1 T
b0 M
b10000000 .
b10000000 I
b10000000 L
b11111111 O
b100 W
b10 _
b11111110 g
b10 o
b11111110 w
b11111100 G
b10000000 E
b1000000 /
b1000000 A
b1000000 D
b11111101 @
b11111111 6
b11111111 F
b11111111 J
b11 H
b10 5
b10 N
b10 R
b11 P
b1 4
b1 V
b1 Z
b11111101 X
b11111111 3
b11111111 ^
b11111111 b
b11111101 `
b1 2
b1 f
b1 j
b11 h
b11111111 1
b11111111 n
b11111111 r
b11111101 p
b1 0
b1 v
b11 x
b1000000 =
b11111110 7
b11111110 >
b11111110 B
b1 ?
b11 #
b11 &
b11 ;
b11 C
b11 K
b11 S
b11 [
b11 c
b11 k
b11 s
b10100000 $
b10100000 '
b10100000 <
#60
b1100100 !
b1100100 9
b1000000 U
b0 e
b0 m
b0 u
b100000 -
b100000 Q
b100000 T
b10000000 +
b10000000 a
b10000000 d
b0 *
b0 i
b0 l
b0 )
b0 q
b0 t
b0 "
b0 8
b0 (
b0 y
b11 O
b100000 M
b110 W
b1100 _
b10000000 ]
b11001 g
b110010 o
b1100100 w
b10010000 E
b1 G
b10010000 .
b10010000 I
b10010000 L
b1000000 ,
b1000000 Y
b1000000 \
b11001000 /
b11001000 A
b11001000 D
b10000000 @
b10000001 6
b10000001 F
b10000001 J
b10000000 H
b10000011 5
b10000011 N
b10000011 R
b10000000 P
b10000110 4
b10000110 V
b10000110 Z
b10000000 X
b10001100 3
b10001100 ^
b10001100 b
b10000000 `
b10011001 2
b10011001 f
b10011001 j
b10000000 h
b10110010 1
b10110010 n
b10110010 r
b10000000 p
b11100100 0
b11100100 v
b10000000 x
b11001000 =
b10000000 7
b10000000 >
b10000000 B
b0 ?
b10000000 #
b10000000 &
b10000000 ;
b10000000 C
b10000000 K
b10000000 S
b10000000 [
b10000000 c
b10000000 k
b10000000 s
b1100100 $
b1100100 '
b1100100 <
#70
b0 !
b0 9
b1 "
b1 8
b1 (
b1 y
b0 u
b10000000 )
b10000000 q
b10000000 t
b10000000 m
b11000000 *
b11000000 i
b11000000 l
b11000000 e
b11100000 +
b11100000 a
b11100000 d
b11100000 ]
b11110000 U
b11110000 ,
b11110000 Y
b11110000 \
b11111000 -
b11111000 Q
b11111000 T
b11111000 M
b11111100 .
b11111100 I
b11111100 L
b11 G
b101 O
b1001 W
b10001 _
b100001 g
b1000001 o
b10000001 w
b11111100 E
b11111110 /
b11111110 A
b11111110 D
b10000001 7
b10000001 >
b10000001 B
b10000001 @
b10000010 6
b10000010 F
b10000010 J
b1111111 H
b10000100 5
b10000100 N
b10000100 R
b1111111 P
b10001000 4
b10001000 V
b10001000 Z
b1111111 X
b10010000 3
b10010000 ^
b10010000 b
b1111111 `
b10100000 2
b10100000 f
b10100000 j
b1111111 h
b11000000 1
b11000000 n
b11000000 r
b1111111 p
b0 0
b0 v
b1111111 x
b11111110 =
b1111111 #
b1111111 &
b1111111 ;
b1111111 C
b1111111 K
b1111111 S
b1111111 [
b1111111 c
b1111111 k
b1111111 s
b1111111 $
b1111111 '
b1111111 <
